{
    "ignore":[
        "null"
    ],
    "purchase_invoices":{
        "invoiceNumber": "RECORDID",
        "number": "DOCNUMBER",
        "lineItems": [
            {
                "productId": "ITEMID",
                "productName": "ITEMNAME",
                "productSku": null,
                "description": "ENTRYDESCRIPTION",
                "quantity": null,
                "unitPrice": null,
                "totalPrice": "TRX_AMOUNT",
                "discountAmount": null,
                "taxAmount": null,
                "taxCode": null,
                "supplierNumber": "VENDORID",
                "supplierCode": "VENDORID",
                "supplierName": "VENDORNAME",
                "departmentId":"DEPARTMENTID",
                "department": "DEPARTMENT",
                "departmentName": "DEPARTMENTNAME",
                "accountId": "ACCOUNTID",
                "accountNumber": "ACCOUNTNO",
                "accountName": "ACCOUNTNAME",
                "classId": "CLASSID",
                "className": "CLASSNAME",
                "projectId": "PROJECTID",
                "projectName": "PROJECTNAME",
                "location": "LOCATIONNAME",
                "locationId": "LOCATIONID",
                "customFields": "customFields",
                "taskId": "TASKID",
                "employeeId": "EMPLOYEENO"
            }
        ],
        "supplierCode": "VENDORID",
        "supplierNumber": "VENDORID",
        "supplierName": "VENDORNAME",
        "currency": "BASECURR",
        "issueDate": "WHENPOSTED",
        "dueDate": "WHENDUE",
        "paidDate": "RECPAYMENTDATE",
        "description": "DESCRIPTION",
        "address": {
            "id": null,
            "name": "LOCATIONNAME",
            "line1": null,
            "line2": null,
            "line3": null,
            "city": null,
            "state": null,
            "postalCode": null,
            "country": null
        },
        "subTotal": null,
        "totalDiscount": null,
        "totalTaxAmount": null,
        "totalAmount": null,
        "amountDue": null,
        "status": "STATE",
        "createdAt": "WHENCREATED",
        "updatedAt": null,
        "location": "LOCATIONNAME",
        "locationId": "LOCATIONID"
    },
    "bills": {
        "number": "DOCNUMBER",
        "description": "DESCRIPTION",
        "status": "STATE",
        "dueDate": "WHENDUE",
        "currency": "BASECURR",
        "paidDate": "RECPAYMENTDATE",
        "subTotal": null,
        "amountDue": null,
        "createdAt": "WHENCREATED",
        "issueDate": "WHENPOSTED",
        "lineItems": [
            {
                "taxCode": null,
                "quantity": null,
                "projectId": "PROJECTID",
                "projectName": "PROJECTNAME",
                "taxAmount": null,
                "unitPrice": null,
                "productSku": null,
                "totalPrice": "TRX_AMOUNT",
                "accountId": "ACCOUNTID",
                "accountNumber": "ACCOUNTNO",
                "accountName": "ACCOUNTNAME",
                "description": "ENTRYDESCRIPTION",
                "productName": "ITEMNAME",
                "productId": "ITEMID",
                "discountAmount": null,
                "locationId": "LOCATIONID",
                "departmentId":"DEPARTMENTID",
                "department": "DEPARTMENT",
                "departmentName": "DEPARTMENTNAME",
                "vendorId":"VENDORID",
                "classId": "CLASSID",
                "className": "CLASSNAME",
                "taskId": "TASKID",
                "customFields": "customFields",
                "employeeId": "EMPLOYEENO"
            }
        ],
        "expenses": [
            {
                "amount": "TRX_AMOUNT",
                "accountId": "ACCOUNTID",
                "accountNumber": "ACCOUNTNO",
                "description": "ENTRYDESCRIPTION",
                "department": "DEPARTMENT",
                "departmentId":"DEPARTMENTID",
                "departmentName": "DEPARTMENTNAME",
                "vendorId":"VENDORID",
                "locationId": "LOCATIONID",
                "classId": "CLASSID",
                "projectId": "PROJECTID",
                "projectName": "PROJECTNAME"
            }
        ],
        "updatedAt": null,
        "vendorName": "VENDORNAME",
        "vendorId": "VENDORID",
        "vendorNum": "VENDORNUMBER",
        "totalAmount": null,
        "vendorBillNumber": "RECORDID",
        "invoiceNumber": "RECORDID",
        "totalDiscount": null,
        "totalTaxAmount": null,
        "location": "LOCATIONNAME",
        "locationId": "LOCATIONID",
        "subsidiary": null
    },
    "journal_entries": {
        "id":null,
        "type": "JOURNAL",
        "transactionDate":"BATCH_DATE",
        "currency":null,
        "departmentId":null,
        "className":null,
        "classId":null,
        "departmentName":null,
        "sourceEntityId": "BASELOCATION_NO",
        "lines":[
            {   
                "accountNumber":"ACCOUNTNO",
                "accountName":"ACCOUNTNAME",
                "customerName":"CUSTOMERNAME",
                "description":"DESCRIPTION",
                "amount":"TRX_AMOUNT",
                "postingType":"TR_TYPE",
                "vendorName":"VENDORNAME",
                "departmentId":"DEPARTMENTID",
                "accountId":"ACCOUNTID",
                "classId":"CLASSID",
                "customerId":"CUSTOMERID",
                "vendorId":"VENDORID",
                "className":"CLASSNAME",
                "department":"DEPARTMENT",
                "departmentName":"DEPARTMENTNAME",
                "locationName": "LOCATIONNAME",
                "locationId": "LOCATION"
            }
        ]
    },
    "account_payable_vendors": {
        "vendorNumber": "VENDORID",
        "vendorName": "NAME",
        "currency": "CURRENCY",
        "note": "COMMENTS",
        "addresses": {
            "line1": "ADDRESS1",
            "city": "CITY",
            "state": "STATE",
            "country": "COUNTRY",
            "postalCode": "ZIP"
        },
        "phones": {
            "number": "PHONE1",
            "type": null
        }
    },
    "apadjustment": {
        "vendorId": "vendorid",
        "transactionDate": "datecreated",
        "status": "action",
        "billNumber": "billno",
        "description": "description",
        "currency": "currency",
        "adjustmentNumber": "adjustmentno",
        "lineItems": [{
            "accountId": "accountid",
            "accountNumber": "glaccountno",
            "accountName": "accountlabel",
            "amount": "amount",
            "memo": "memo",
            "vendorId": "vendorid",
            "vendorName": "vendorname",
            "projectId": "projectid",
            "projectName": "projectname",
            "locationName": "locationname",
            "locationId": "locationid",
            "classId": "classid",
            "className": "classname",
            "departmentId": "departmentid",
            "departmentName": "departmentname"
        }]
    },
    "purchase_orders": {
        "id": "RECORDNO",
        "transactionDate": "datecreated",
        "vendorId": "vendorid",
        "vendorName": "vendorname",
        "number": "documentno",
        "referenceNumber": "referenceno",
        "paymentTerm": "termname",
        "dueDate": "datedue",
        "description": "message",
        "currency": "basecurr",
        "lineItems": [{
            "productId": "itemid",
            "quantity": "quantity",
            "unitPrice": "price",
            "taxAmount": "tax",
            "locationId": "locationid",
            "locationName": "locationname",
            "departmentId": "departmentid",
            "departmentName": "departmentname",
            "description": "memo",
            "projectId": "projectid",
            "projectName": "projectname",
            "employeeId": "employeeid",
            "classId": "classid",
            "className": "classname"
        }]    
    }
}
